{"TbOpendataFixedcctvGB":{"list_total_count":105,"RESULT":{"CODE":"INFO-000","MESSAGE":"정상 처리되었습니다"},"row":[{"FIX_CCTV_ADDR":"강북구 미아동 838-19","LAT":"37.6200256347656","LOT":"127.018348693847","CGG_CD":"강북구","CRDN_BRNCH_NM":"주정차(삼양)-306 (솔샘로 229-1, 미양 온누리약국 앞)","GRNDS_SE":"불법주정차구역"},{"FIX_CCTV_ADDR":"미아동 158-10","LAT":"37.63475037","LOT":"127.0255814","CGG_CD":"강북구","CRDN_BRNCH_NM":"주정차(미아)-059 (덕릉로 108, 강북 여성인력 개발센터)","GRNDS_SE":"불법주정차구역"},{"FIX_CCTV_ADDR":"미아동 125-61","LAT":"37.62513351","LOT":"127.0282898","CGG_CD":"강북구","CRDN_BRNCH_NM":"주정차(미아)-017 (솔매로52길 31, 애화학교 앞)","GRNDS_SE":"불법주정차구역"},{"FIX_CCTV_ADDR":"미아동 125-9","LAT":"37.6245842","LOT":"127.0277252","CGG_CD":"강북구","CRDN_BRNCH_NM":"주정차(미아)-018 (솔매로50길 43, KT강북플라자 앞)","GRNDS_SE":"불법주정차구역"},{"FIX_CCTV_ADDR":"번1동 460-46","LAT":"37.63733292","LOT":"127.0326614","CGG_CD":"강북구","CRDN_BRNCH_NM":"주정차(번1)-033 (한천로124길 14, 수송초 정문)","GRNDS_SE":"불법주정차구역"},{"FIX_CCTV_ADDR":"번1동 454-58","LAT":"37.63640213","LOT":"127.0339661","CGG_CD":"강북구","CRDN_BRNCH_NM":"주정차(번1)-034 (한천로122길 21, 수송중 옆)","GRNDS_SE":"불법주정차구역"},{"FIX_CCTV_ADDR":"번1동 428-87","LAT":"37.6346817","LOT":"127.0358429","CGG_CD":"강북구","CRDN_BRNCH_NM":"주정차(번1)-026 (한천로 940, 번동 프라자약국 옆)","GRNDS_SE":"불법주정차구역"},{"FIX_CCTV_ADDR":"번동 417-32","LAT":"37.63895798","LOT":"127.0281448","CGG_CD":"강북구","CRDN_BRNCH_NM":"주정차(번1)-050 (한천로 1019, 토마토24시)","GRNDS_SE":"불법주정차구역"},{"FIX_CCTV_ADDR":"번동 415-15","LAT":"37.63714981","LOT":"127.0269928","CGG_CD":"강북구","CRDN_BRNCH_NM":"주정차(번1)-051 (오패산로 406, 강북경찰서 앞)","GRNDS_SE":"불법주정차구역"},{"FIX_CCTV_ADDR":"번동 414-25","LAT":"37.63624573","LOT":"127.028244","CGG_CD":"강북구","CRDN_BRNCH_NM":"주정차(번1)-052 (오패산로 390, GS25시)","GRNDS_SE":"불법주정차구역"},{"FIX_CCTV_ADDR":"강북구 번동 236","LAT":"37.62935938540034","LOT":"127.04003928682246","CGG_CD":"강북구","CRDN_BRNCH_NM":"주정차(번2)-010 (오현로 204, 벌말어린이공원 입구)","GRNDS_SE":"불법주정차구역"},{"FIX_CCTV_ADDR":"번2동 520","LAT":"37.63386154","LOT":"127.0320206","CGG_CD":"강북구","CRDN_BRNCH_NM":"주정차(번2)-019 (덕릉로40길 48, 번2동 어린이집 앞)","GRNDS_SE":"불법주정차구역"},{"FIX_CCTV_ADDR":"번2동 234-2","LAT":"37.63211823","LOT":"127.0381012","CGG_CD":"강북구","CRDN_BRNCH_NM":"주정차(번2)-020 (오현로35길 62, 꿈동산어린이집 앞)","GRNDS_SE":"불법주정차구역"},{"FIX_CCTV_ADDR":"강북구 번동 148-375","LAT":"37.625122201005155","LOT":"127.03378118648361","CGG_CD":"강북구","CRDN_BRNCH_NM":"주정차(번2)-025 (오현로21길 66, 번동공영주차장지하2층)","GRNDS_SE":"불법주정차구역"},{"FIX_CCTV_ADDR":"강북구 번동 148-349","LAT":"37.62507510769596","LOT":"127.0330448527526","CGG_CD":"강북구","CRDN_BRNCH_NM":"주정차(번2)-026 (오현로21길 88, 번동공영주차장지상2층)","GRNDS_SE":"불법주정차구역"},{"FIX_CCTV_ADDR":"강북구 번동 산 27-117","LAT":"37.62485205696906","LOT":"127.03324582334189","CGG_CD":"강북구","CRDN_BRNCH_NM":"주정차(번2)-027 (오현로21길 79, 번동공영주차장코너)","GRNDS_SE":"불법주정차구역"},{"FIX_CCTV_ADDR":"번2동 437-13","LAT":"37.63500214","LOT":"127.0290909","CGG_CD":"강북구","CRDN_BRNCH_NM":"주정차(번2)-049 (덕릉로 136, 창강빌딩 앞)","GRNDS_SE":"불법주정차구역"},{"FIX_CCTV_ADDR":"번2동 433-15","LAT":"37.63518524","LOT":"127.0318909","CGG_CD":"강북구","CRDN_BRNCH_NM":"주정차(번2)-050 (덕릉로 162, 강북 북부시장)","GRNDS_SE":"불법주정차구역"},{"FIX_CCTV_ADDR":"번3동 248","LAT":"37.62340927","LOT":"127.0460739","CGG_CD":"강북구","CRDN_BRNCH_NM":"주정차(번3)-006 (월계로 221, 오현초 후문)","GRNDS_SE":"불법주정차구역"},{"FIX_CCTV_ADDR":"번3동 155-4","LAT":"37.62821579","LOT":"127.0389252","CGG_CD":"강북구","CRDN_BRNCH_NM":"주정차(번3)-013 (오현로 186, 번동 평화교회 앞)","GRNDS_SE":"불법주정차구역"},{"FIX_CCTV_ADDR":"번3동 657","LAT":"37.62379074","LOT":"127.0377274","CGG_CD":"강북구","CRDN_BRNCH_NM":"주정차(번3)-016 (오현로 128, 동문아파트)","GRNDS_SE":"불법주정차구역"},{"FIX_CCTV_ADDR":"강북구 번동 122-6","LAT":"37.6227431932927","LOT":"127.03778014377","CGG_CD":"강북구","CRDN_BRNCH_NM":"주정차(번3)-017 (번동 120-6, 꿈의숲서문아트센터)","GRNDS_SE":"불법주정차구역"},{"FIX_CCTV_ADDR":"강북구 미아동 561-2","LAT":"37.6175815158732","LOT":"127.02173885886374","CGG_CD":"강북구","CRDN_BRNCH_NM":"주정차(송천)-191 (삼양로24길 19, 송천동 성당 앞)","GRNDS_SE":"불법주정차구역"},{"FIX_CCTV_ADDR":"번동 242-3","LAT":"37.62527466","LOT":"127.0452118","CGG_CD":"강북구","CRDN_BRNCH_NM":"주정차(번3)-026 (한천로105길33,한진아파트입구건너편)","GRNDS_SE":"불법주정차구역"},{"FIX_CCTV_ADDR":"번동 242-3","LAT":"37.62598801","LOT":"127.0464935","CGG_CD":"강북구","CRDN_BRNCH_NM":"주정차(번3)-027 (한천로105길 21, 번3동 주민센터 앞)","GRNDS_SE":"불법주정차구역"},{"FIX_CCTV_ADDR":"삼각산동 1353-8","LAT":"37.61703873","LOT":"127.0152893","CGG_CD":"강북구","CRDN_BRNCH_NM":"주정차(삼각산)-005 (삼양로19길 154, 보건소 삼각산분소 앞)","GRNDS_SE":"불법주정차구역"},{"FIX_CCTV_ADDR":"삼각산동 1353","LAT":"37.61941147","LOT":"127.0106659","CGG_CD":"강북구","CRDN_BRNCH_NM":"주정차(삼각산)-007 (솔샘로 174, 벽산라이브파크 정문 건너편)","GRNDS_SE":"불법주정차구역"},{"FIX_CCTV_ADDR":"삼각산동 699-22","LAT":"37.61923599","LOT":"127.0180435","CGG_CD":"강북구","CRDN_BRNCH_NM":"주정차(삼각산)-021 (솔샘로48길17-3)","GRNDS_SE":"불법주정차구역"},{"FIX_CCTV_ADDR":"강북구 미아동 811","LAT":"37.61889764012865","LOT":"127.01765446201478","CGG_CD":"강북구","CRDN_BRNCH_NM":"주정차(삼각산)-022 (삼양로27길 95, 두산위브 213동 앞 사거리)","GRNDS_SE":"불법주정차구역"},{"FIX_CCTV_ADDR":"삼각산동811-9 ","LAT":"37.61886597","LOT":"127.0192566","CGG_CD":"강북구","CRDN_BRNCH_NM":"주정차(삼각산)-023 (삼양로27길 43, 솔샘시장 입구)","GRNDS_SE":"불법주정차구역"},{"FIX_CCTV_ADDR":"삼각산동 812-1","LAT":"37.61835098","LOT":"127.0191422","CGG_CD":"강북구","CRDN_BRNCH_NM":"주정차(삼각산)-024 (삼양로27길35, 삼양제일교회 후문 앞)","GRNDS_SE":"불법주정차구역"},{"FIX_CCTV_ADDR":"삼각산동 812","LAT":"37.61876678","LOT":"127.0203552","CGG_CD":"강북구","CRDN_BRNCH_NM":"주정차(삼각산)-025 (삼양로27길19 , 래미안아파트 2차 입구)","GRNDS_SE":"불법주정차구역"},{"FIX_CCTV_ADDR":"삼각산동1353-6","LAT":"37.6200943","LOT":"127.0153656","CGG_CD":"강북구","CRDN_BRNCH_NM":"주정차(삼각산)-027 (솔샘로 208, 미아 안전센터 앞)","GRNDS_SE":"불법주정차구역"},{"FIX_CCTV_ADDR":"삼양동776-130 ","LAT":"37.62355042","LOT":"127.0186157","CGG_CD":"강북구","CRDN_BRNCH_NM":"주정차(삼양)-015 (삼양로 225, 삼양초 정문)","GRNDS_SE":"불법주정차구역"},{"FIX_CCTV_ADDR":"삼양동 791-2127","LAT":"37.62159348","LOT":"127.0172577","CGG_CD":"강북구","CRDN_BRNCH_NM":"주정차(삼양)-023 (삼양로41길 54, 솔바람어린이집 옆)","GRNDS_SE":"불법주정차구역"},{"FIX_CCTV_ADDR":"송중동 126-41","LAT":"37.62304913554194","LOT":"127.0282353999178","CGG_CD":"강북구","CRDN_BRNCH_NM":"주정차(송중)-019 (솔매로50길 78, 윤선생영어숲 화계점)","GRNDS_SE":"불법주정차구역"},{"FIX_CCTV_ADDR":"송중동 100-33","LAT":"37.61746216","LOT":"127.0317993","CGG_CD":"강북구","CRDN_BRNCH_NM":"주정차(송중)-020 (오현로 9, 송중초 후문)","GRNDS_SE":"불법주정차구역"},{"FIX_CCTV_ADDR":"송중동 103-137","LAT":"37.61836624","LOT":"127.0329666","CGG_CD":"강북구","CRDN_BRNCH_NM":"주정차(송중)-038 (오패산로 187, 효성어린이집 앞)","GRNDS_SE":"불법주정차구역"},{"FIX_CCTV_ADDR":"송중동 3-8","LAT":"37.61785507","LOT":"127.0337219","CGG_CD":"강북구","CRDN_BRNCH_NM":"주정차(송중)-039 (오현로9길 27, 예원어린이집 정문)","GRNDS_SE":"불법주정차구역"},{"FIX_CCTV_ADDR":"송중동 3-865","LAT":"37.61660004","LOT":"127.033577","CGG_CD":"강북구","CRDN_BRNCH_NM":"주정차(송중)-036 (오현로 31, 삼화그린빌라 앞)","GRNDS_SE":"불법주정차구역"},{"FIX_CCTV_ADDR":"송중동 53-1","LAT":"37.61371231","LOT":"127.0340729","CGG_CD":"강북구","CRDN_BRNCH_NM":"주정차(송중)-037 (오패산로 130, 동명빌딩(주차장))","GRNDS_SE":"불법주정차구역"},{"FIX_CCTV_ADDR":"송중동 860-213","LAT":"37.61286163","LOT":"127.0304565","CGG_CD":"강북구","CRDN_BRNCH_NM":"주정차(송중)-023 (도봉로8길 8, 미아사거리역 2번 출구 앞)","GRNDS_SE":"불법주정차구역"},{"FIX_CCTV_ADDR":"송중동 860-17","LAT":"37.61216354","LOT":"127.0318985","CGG_CD":"강북구","CRDN_BRNCH_NM":"주정차(송중)-043 (도봉로8길 32 , 삼가네맷돌빈대떡)","GRNDS_SE":"불법주정차구역"},{"FIX_CCTV_ADDR":"송중동 860-172","LAT":"37.61585617","LOT":"127.0307617","CGG_CD":"강북구","CRDN_BRNCH_NM":"주정차(송중)-021 (도봉로10길 73, 햇빛병원 뒷편)","GRNDS_SE":"불법주정차구역"},{"FIX_CCTV_ADDR":"송중동 70-6","LAT":"37.61468124","LOT":"127.0307922","CGG_CD":"강북구","CRDN_BRNCH_NM":"주정차(송중)-022 (도봉로10길 46, 롯데백화점 후문)","GRNDS_SE":"불법주정차구역"},{"FIX_CCTV_ADDR":"송중동 128-56","LAT":"37.6235199","LOT":"127.0296249","CGG_CD":"강북구","CRDN_BRNCH_NM":"주정차(송중)-075 (솔매로50가길 25, 화계초등학교 정문 앞)","GRNDS_SE":"불법주정차구역"},{"FIX_CCTV_ADDR":"송중동 84-29","LAT":"37.6157341","LOT":"127.0351181","CGG_CD":"강북구","CRDN_BRNCH_NM":"주정차(송중)-129 (오패산로30길 55, 경남아너스빌 앞)","GRNDS_SE":"불법주정차구역"},{"FIX_CCTV_ADDR":"송중동 83-4","LAT":"37.61407471","LOT":"127.0349045","CGG_CD":"강북구","CRDN_BRNCH_NM":"주정차(송중)-130 (오패산로30길 21 앞)","GRNDS_SE":"불법주정차구역"},{"FIX_CCTV_ADDR":"송천동62-21 ","LAT":"37.61502457","LOT":"127.0292892","CGG_CD":"강북구","CRDN_BRNCH_NM":"주정차(송천)-019 (도봉로13길 22, 고려새한병원 뒤)","GRNDS_SE":"불법주정차구역"},{"FIX_CCTV_ADDR":"송천동 637-290","LAT":"37.61426163","LOT":"127.0222778","CGG_CD":"강북구","CRDN_BRNCH_NM":"주정차(송천)-018 (삼양로 116, 삼성부동산 앞)","GRNDS_SE":"불법주정차구역"},{"FIX_CCTV_ADDR":"송천동 471-14","LAT":"37.6133194","LOT":"127.0272369","CGG_CD":"강북구","CRDN_BRNCH_NM":"주정차(송천)-028 (숭인로13길 27-2 , 영훈초등학교 후문 앞)","GRNDS_SE":"불법주정차구역"},{"FIX_CCTV_ADDR":"송천동 320-1","LAT":"37.62000275","LOT":"127.0250854","CGG_CD":"강북구","CRDN_BRNCH_NM":"주정차(송천)-030 (도봉로29길 52, 별밭어린이집 앞)","GRNDS_SE":"불법주정차구역"},{"FIX_CCTV_ADDR":"송천동 860-75","LAT":"37.61928558","LOT":"127.0213547","CGG_CD":"강북구","CRDN_BRNCH_NM":"주정차(송천)-063 (솔샘로 255, 삼양사거리)","GRNDS_SE":"불법주정차구역"},{"FIX_CCTV_ADDR":"송천동 707-53","LAT":"37.61845016","LOT":"127.0239105","CGG_CD":"강북구","CRDN_BRNCH_NM":"주정차(송천)-064 (솔샘로 277-4, 강북재활용)","GRNDS_SE":"불법주정차구역"},{"FIX_CCTV_ADDR":"송천동 329-6","LAT":"37.61814117","LOT":"127.0257111","CGG_CD":"강북구","CRDN_BRNCH_NM":"주정차(송천)-065 (솔샘로 299 앞)","GRNDS_SE":"불법주정차구역"},{"FIX_CCTV_ADDR":"송천동 373-54","LAT":"37.6170845","LOT":"127.0278168","CGG_CD":"강북구","CRDN_BRNCH_NM":"주정차(송천)-066 (솔샘로 315 신성교회 옆)","GRNDS_SE":"불법주정차구역"},{"FIX_CCTV_ADDR":"송천동 65-5","LAT":"37.61705017","LOT":"127.0288239","CGG_CD":"강북구","CRDN_BRNCH_NM":"주정차(송천)-067 (솔샘로 330 앞)","GRNDS_SE":"불법주정차구역"},{"FIX_CCTV_ADDR":"수유1동 486-791","LAT":"37.62798891008133","LOT":"127.01545325275974","CGG_CD":"강북구","CRDN_BRNCH_NM":"주정차(수유1)-019 (삼양로73가길 58 맞은편, 한빛사랑관)","GRNDS_SE":"불법주정차구역"},{"FIX_CCTV_ADDR":"수유1동 52-21","LAT":"37.63218307","LOT":"127.021698","CGG_CD":"강북구","CRDN_BRNCH_NM":"주정차(수유1)-021 (수유로4길 58, 수유시장새마을금고)","GRNDS_SE":"불법주정차구역"},{"FIX_CCTV_ADDR":"수유1동56-129 ","LAT":"37.63167953","LOT":"127.0196991","CGG_CD":"강북구","CRDN_BRNCH_NM":"주정차(수유1)-022 (삼양로80나길 14, 나나어린이집)","GRNDS_SE":"불법주정차구역"},{"FIX_CCTV_ADDR":"수유1동 605-435","LAT":"37.62913132","LOT":"127.0164948","CGG_CD":"강북구","CRDN_BRNCH_NM":"주정차(수유1)-018 (삼양로77가길 28, 진산빌라 앞)","GRNDS_SE":"불법주정차구역"},{"FIX_CCTV_ADDR":"수유1동 55-47","LAT":"37.63017273","LOT":"127.0211716","CGG_CD":"강북구","CRDN_BRNCH_NM":"주정차(수유1)-023 (삼양로74다길 2, 수유초 정문)","GRNDS_SE":"불법주정차구역"},{"FIX_CCTV_ADDR":"수유1동 58-1","LAT":"37.63108444","LOT":"127.0193863","CGG_CD":"강북구","CRDN_BRNCH_NM":"주정차(수유1)-020 (삼양로80길 26, 수유초 후문)","GRNDS_SE":"불법주정차구역"},{"FIX_CCTV_ADDR":"수유1동 605-389","LAT":"37.63080597","LOT":"127.0170517","CGG_CD":"강북구","CRDN_BRNCH_NM":"주정차(수유1)-031 (삼양로79길 10, 신기어린이집 앞)","GRNDS_SE":"불법주정차구역"},{"FIX_CCTV_ADDR":"강북구 수유동 486-135","LAT":"37.6283165984998","LOT":"127.013232675754","CGG_CD":"강북구","CRDN_BRNCH_NM":"주정차(수유1)-118 (삼양로77가길 90, 삼흥연립 앞)","GRNDS_SE":"불법주정차구역"},{"FIX_CCTV_ADDR":"수유동 486-251","LAT":"37.62868881","LOT":"127.0150604","CGG_CD":"강북구","CRDN_BRNCH_NM":"주정차(수유1)-119 (삼양로77길 66, 빨래골 방앗간 앞)","GRNDS_SE":"불법주정차구역"},{"FIX_CCTV_ADDR":"수유동 480-29","LAT":"37.62946701","LOT":"127.0162582","CGG_CD":"강북구","CRDN_BRNCH_NM":"주정차(수유1)-120 (삼양로77길 38, 한빛예술단)","GRNDS_SE":"불법주정차구역"},{"FIX_CCTV_ADDR":"수유2동 246-10","LAT":"37.64401627","LOT":"127.0189209","CGG_CD":"강북구","CRDN_BRNCH_NM":"주정차(수유2)-020 (한천로155길 42, 굿모닝마트 맞은편)","GRNDS_SE":"불법주정차구역"},{"FIX_CCTV_ADDR":"수유2동 246-13","LAT":"37.64379883","LOT":"127.0193939","CGG_CD":"강북구","CRDN_BRNCH_NM":"주정차(수유2)-022 (한천로155길 38, 푸른솔어린이집 앞)","GRNDS_SE":"불법주정차구역"},{"FIX_CCTV_ADDR":"수유2동 234","LAT":"37.64229584","LOT":"127.0217972","CGG_CD":"강북구","CRDN_BRNCH_NM":"주정차(수유2)-021 (삼각산로 161, 성체유치원 정문)","GRNDS_SE":"불법주정차구역"},{"FIX_CCTV_ADDR":"수유3동 189-1","LAT":"37.64208984","LOT":"127.0236664","CGG_CD":"강북구","CRDN_BRNCH_NM":"주정차(수유3)-034 (한천로 1073, 고신경외과 앞)","GRNDS_SE":"불법주정차구역"},{"FIX_CCTV_ADDR":"수유3동 189-35","LAT":"37.64109802","LOT":"127.025032","CGG_CD":"강북구","CRDN_BRNCH_NM":"주정차(수유3)-035 (한천로 1057, 삼천리자전거앞)","GRNDS_SE":"불법주정차구역"},{"FIX_CCTV_ADDR":"수유3동 190-9","LAT":"37.64006805","LOT":"127.0264893","CGG_CD":"강북구","CRDN_BRNCH_NM":"주정차(수유3)-036 (한천로 1039, 파리바게트앞)","GRNDS_SE":"불법주정차구역"},{"FIX_CCTV_ADDR":"수유3동192-4번지","LAT":"37.63864136","LOT":"127.0247421","CGG_CD":"강북구","CRDN_BRNCH_NM":"주정차(수유3)-056 (한천로139길 46, CU 수유중앙점앞)","GRNDS_SE":"불법주정차구역"},{"FIX_CCTV_ADDR":"수유동 191-70","LAT":"37.63916779","LOT":"127.0257645","CGG_CD":"강북구","CRDN_BRNCH_NM":"주정차(수유3)-055 (한천로139길 25, 강북구청)","GRNDS_SE":"불법주정차구역"},{"FIX_CCTV_ADDR":"우이동 산37","LAT":"37.65959167","LOT":"127.0114746","CGG_CD":"강북구","CRDN_BRNCH_NM":"주정차(우이)-034 (삼양로163길 51, 제일어린이집)","GRNDS_SE":"불법주정차구역"},{"FIX_CCTV_ADDR":"우이동139-14 ","LAT":"37.65955353","LOT":"127.010788","CGG_CD":"강북구","CRDN_BRNCH_NM":"주정차(우이)-033 (삼양로159길 60-18, 제일어린이집 앞)","GRNDS_SE":"불법주정차구역"},{"FIX_CCTV_ADDR":"우이동 94-21","LAT":"37.6540184","LOT":"127.0117645","CGG_CD":"강북구","CRDN_BRNCH_NM":"주정차(우이)-035 (삼양로149길 12 앞, 솔밭 어린이집 앞)","GRNDS_SE":"불법주정차구역"},{"FIX_CCTV_ADDR":"인수동 395-7","LAT":"37.63789368","LOT":"127.0160904","CGG_CD":"강북구","CRDN_BRNCH_NM":"주정차(인수)-018 (삼양로93길 19 앞)","GRNDS_SE":"불법주정차구역"},{"FIX_CCTV_ADDR":"인수동 394-11","LAT":"37.63855362","LOT":"127.0159225","CGG_CD":"강북구","CRDN_BRNCH_NM":"주정차(인수)-017 (삼양로99길 33 앞)","GRNDS_SE":"불법주정차구역"},{"FIX_CCTV_ADDR":"인수동 554-92 건너편","LAT":"37.64319992","LOT":"127.0108337","CGG_CD":"강북구","CRDN_BRNCH_NM":"주정차(인수)-019 (인수봉로 269 앞)","GRNDS_SE":"불법주정차구역"},{"FIX_CCTV_ADDR":"인수동 540-1","LAT":"37.64339066","LOT":"127.0095749","CGG_CD":"강북구","CRDN_BRNCH_NM":"주정차(인수)-020 (인수봉로75길 10 앞)","GRNDS_SE":"불법주정차구역"},{"FIX_CCTV_ADDR":"인수동 119-3","LAT":"37.63443756","LOT":"127.0187149","CGG_CD":"강북구","CRDN_BRNCH_NM":"주정차(인수)-045 (덕릉로 45, 화계유치원 앞)","GRNDS_SE":"불법주정차구역"},{"FIX_CCTV_ADDR":"인수동 349-13","LAT":"37.64137268","LOT":"127.0144196","CGG_CD":"강북구","CRDN_BRNCH_NM":"주정차(인수)-046 (삼양로107길 38, 인수동 어린이집 앞)","GRNDS_SE":"불법주정차구역"},{"FIX_CCTV_ADDR":"인수동 545","LAT":"37.64447403","LOT":"127.0106354","CGG_CD":"강북구","CRDN_BRNCH_NM":"주정차(인수)-052 (인수봉로 289 앞)","GRNDS_SE":"불법주정차구역"},{"FIX_CCTV_ADDR":"인수동 551-22 건너편","LAT":"37.6419487","LOT":"127.0110245","CGG_CD":"강북구","CRDN_BRNCH_NM":"주정차(인수)-054 (인수봉로 260, 극동 유치원 앞)","GRNDS_SE":"불법주정차구역"},{"FIX_CCTV_ADDR":"미아동195-3","LAT":"37.630554","LOT":"127.026970","CGG_CD":"강북구","CRDN_BRNCH_NM":"주정차(미아)-073 (솔매로49길 20 후문 앞)","GRNDS_SE":"불법주정차구역"},{"FIX_CCTV_ADDR":"수유동 54-12","LAT":"37.630745","LOT":"127.023729","CGG_CD":"강북구","CRDN_BRNCH_NM":"주정차(수유1)-043 (도봉로67길13,수유시장(남문1)입구)","GRNDS_SE":"불법주정차구역"},{"FIX_CCTV_ADDR":"수유동 55-7","LAT":"37.630708","LOT":"127.023716","CGG_CD":"강북구","CRDN_BRNCH_NM":"주정차(수유1)-048 (도봉로67길 34, 수유시장 주차장 입구)","GRNDS_SE":"불법주정차구역"},{"FIX_CCTV_ADDR":"강북구 수유동 386-2","LAT":"37.6406021118164","LOT":"127.017051696777","CGG_CD":"강북구","CRDN_BRNCH_NM":"주정차(수유3)-129 (삼양로 416, 가오리소방서)","GRNDS_SE":"불법주정차구역"},{"FIX_CCTV_ADDR":"강북구 우이동 71-36","LAT":"37.6516876220703","LOT":"127.011878967285","CGG_CD":"강북구","CRDN_BRNCH_NM":"주정차(우이)-200 (삼양로 561, 솔밭근린공원놀이터)","GRNDS_SE":"불법주정차구역"},{"FIX_CCTV_ADDR":"강북구 수유동 486-805","LAT":"37.6277542114257","LOT":"127.011108398437","CGG_CD":"강북구","CRDN_BRNCH_NM":"주정차(수유1)-207 (인수봉로23길 28, SH스카이아파트 앞)","GRNDS_SE":"불법주정차구역"},{"FIX_CCTV_ADDR":"강북구 수유동 409-6","LAT":"37.6386546815398","LOT":"127.014808238461","CGG_CD":"강북구","CRDN_BRNCH_NM":"주정차(인수)-265(삼양로99길36우이초 후문)","GRNDS_SE":"불법주정차구역"},{"FIX_CCTV_ADDR":"강북구 미아동 756-1","LAT":"37.6240064830504","LOT":"127.019538847238","CGG_CD":"강북구","CRDN_BRNCH_NM":"주정차(송천)-163(삼양로54길 19 냉천길공영주차장)","GRNDS_SE":"불법주정차구역"},{"FIX_CCTV_ADDR":"강북구 미아동 439-138","LAT":"37.6145632473928","LOT":"127.025152856265","CGG_CD":"강북구","CRDN_BRNCH_NM":"주정차(송천)-162(숭인로7나길23)","GRNDS_SE":"불법주정차구역"},{"FIX_CCTV_ADDR":"강북구 미아동 754-63","LAT":"37.62328133219","LOT":"127.021310522429","CGG_CD":"강북구","CRDN_BRNCH_NM":"주정차(송천)-193 (삼양로54길 60, 큰마을효심경로당)","GRNDS_SE":"불법주정차구역"},{"FIX_CCTV_ADDR":"강북구 번동 526-59","LAT":"37.63408805248161","LOT":"127.02993613166709","CGG_CD":"강북구","CRDN_BRNCH_NM":"주정차(번2)-191(덕릉로40다길13, 번동제일교회 앞)","GRNDS_SE":"불법주정차구역"},{"FIX_CCTV_ADDR":"강북구 미아동 318-5","LAT":"37.62186240866289","LOT":"127.02684734506785","CGG_CD":"강북구","CRDN_BRNCH_NM":"주정차(송천)-205(도봉로33길18, 성북프라자 앞)","GRNDS_SE":"불법주정차구역"},{"FIX_CCTV_ADDR":"강북구 우이동 265","LAT":"37.66113914592847","LOT":"127.00736810169097","CGG_CD":"강북구","CRDN_BRNCH_NM":"주정차(우이)-325(삼양로173길112, 북한산국립공원우이분소 앞)","GRNDS_SE":"불법주정차구역"},{"FIX_CCTV_ADDR":"강북구 우이동 181-2","LAT":"37.662240435987215","LOT":"127.00958958221867","CGG_CD":"강북구","CRDN_BRNCH_NM":"주정차(우이)-278(삼양로173길66, 우이맨숀 앞)","GRNDS_SE":"불법주정차구역"},{"FIX_CCTV_ADDR":"강북구 미아동 474","LAT":"37.61314779317265","LOT":"127.02598909324084","CGG_CD":"강북구","CRDN_BRNCH_NM":"주정차(송천)-252(숭인로7가길 37,미아동부센트레빌)","GRNDS_SE":"불법주정차구역"},{"FIX_CCTV_ADDR":"강북구 우이동 4-1","LAT":"37.66392730338878","LOT":"127.01199256173402","CGG_CD":"강북구","CRDN_BRNCH_NM":"주정차(우이)-331(삼양로 685, 우이동견인차량보관소 맞은편)","GRNDS_SE":"불법주정차구역"},{"FIX_CCTV_ADDR":"강북구 번동 442-6","LAT":"37.63395102555836","LOT":"127.02842645670192","CGG_CD":"강북구","CRDN_BRNCH_NM":"주정차(번2)-190(덕릉로36길22-4, 선향사 입구)","GRNDS_SE":"불법주정차구역"},{"FIX_CCTV_ADDR":"강북구 우이동 16-4","LAT":"37.6631141411706","LOT":"127.01225310513348","CGG_CD":"강북구","CRDN_BRNCH_NM":"주정차(우이)-279(삼양로173길7, 삼양교통 앞)","GRNDS_SE":"불법주정차구역"},{"FIX_CCTV_ADDR":"강북구 미아동 1267-20","LAT":"37.61608183702192","LOT":"127.01903846323673","CGG_CD":"강북구","CRDN_BRNCH_NM":"주정차(삼각산)-074(삼양로19길 69, 삼각산아이원 앞) ","GRNDS_SE":"불법주정차구역"}]}}
